Templates/controller.v

module controller(
input clk,                 //clock
input rst_n,               //external reset
input done_1,              //
input done_2,
input start,               //external start command
output trigger_1,          //
output trigger_2
);

parameter [1:0] IDLE = 2'b00, SLAVE_1 = 2'b01, SLAVE_2 = 2'b10;
reg [1:0] CS, NS;

always @(posedge clk or negedge rst_n)
begin
 if (~rst_n)
  CS <= IDLE;
 else CS <= NS;
end

always @(start, done_1, done_2)
begin
 case(CS)
 IDLE: begin
        if (start == 1'b1)
         NS = SLAVE_1;
        else NS = IDLE;
       end
 SLAVE_1: begin
               if (done_1 == 1'b1)
                NS = SLAVE_2;
               else NS = SLAVE_1;
              end
 SLAVE_2: begin
               if (done_2 == 1'b1)
                NS = IDLE;
               else NS = SLAVE_2;
             end
 default: NS = IDLE;
 endcase
end

assign trigger_1 = (CS == SLAVE_1) ? 1'b1 : 1'b0; 
assign trigger_2 = (CS == SLAVE_2) ? 1'b1 : 1'b0; 

endmodule

Templates/slave_1.v

module slave_1(
 input              clk,
 input              rst_n,
 input              slave_en,
 output             slave_done,
 output reg [3:0]   slave_out
);
always @(posedge clk or negedge rst_n)
begin
 if (~rst_n)
  slave_out <= 0;
 else if (slave_en)
  slave_out <= slave_out + 1;
 else slave_out <= 0;
end
assign slave_done = (slave_out == 4) ? 1'b1 : 1'b0;
endmodule

Templates/controller_tb.v


module controller_tb();

reg clk, rst_n, start;
wire done_1, done_2, trigger_1, trigger_2;
wire [3:0] slave_out_1, slave_out_2;

slave_1 one (clk, rst_n, trigger_1, done_1, slave_out_1);
slave_1 two (clk, rst_n, trigger_2, done_2, slave_out_2);
controller control (clk, rst_n, done_1, done_2, start, trigger_1, trigger_2);

initial 
begin
 $dumpfile("controller_tb.vcd");
 $dumpvars(0, controller_tb);

 rst_n = 0;
 start = 0;
 #10;
 rst_n = 1;
 start = 1;
 #200;
 $finish;
end

always
begin
 clk = 1'b1;
 #5;
 clk = 1'b0;
 #5;
end
endmodule

Templates/controller_tb.vcd
$date
	Fri Apr 16 16:11:58 2021
$end
$version
	Icarus Verilog
$end
$timescale
	1s
$end
$scope module controller_tb $end
$var wire 1 ! trigger_2 $end
$var wire 1 " trigger_1 $end
$var wire 4 # slave_out_2 [3:0] $end
$var wire 4 $ slave_out_1 [3:0] $end
$var wire 1 % done_2 $end
$var wire 1 & done_1 $end
$var reg 1 ' clk $end
$var reg 1 ( rst_n $end
$var reg 1 ) start $end
$scope module control $end
$var wire 1 ' clk $end
$var wire 1 ( rst_n $end
$var wire 1 ) start $end
$var wire 1 ! trigger_2 $end
$var wire 1 " trigger_1 $end
$var wire 1 % done_2 $end
$var wire 1 & done_1 $end
$var reg 2 * CS [1:0] $end
$var reg 2 + NS [1:0] $end
$upscope $end
$scope module one $end
$var wire 1 ' clk $end
$var wire 1 ( rst_n $end
$var wire 1 " slave_en $end
$var wire 1 & slave_done $end
$var reg 4 , slave_out [3:0] $end
$upscope $end
$scope module two $end
$var wire 1 ' clk $end
$var wire 1 ( rst_n $end
$var wire 1 ! slave_en $end
$var wire 1 % slave_done $end
$var reg 4 - slave_out [3:0] $end
$upscope $end
$upscope $end
$enddefinitions $end
#0
$dumpvars
b0 -
b0 ,
b0 +
b0 *
0)
0(
1'
0&
0%
b0 $
b0 #
0"
0!
$end
#5
0'
#10
1"
b1 *
b1 +
1'
1)
1(
#15
0'
#20
b1 $
b1 ,
1'
#25
0'
#30
b10 $
b10 ,
1'
#35
0'
#40
b11 $
b11 ,
1'
#45
0'
#50
b10 +
1&
b100 $
b100 ,
1'
#55
0'
#60
0&
0"
1!
b101 $
b101 ,
b10 *
1'
#65
0'
#70
b1 #
b1 -
b0 $
b0 ,
1'
#75
0'
#80
b10 #
b10 -
1'
#85
0'
#90
b11 #
b11 -
1'
#95
0'
#100
b0 +
1%
b100 #
b100 -
1'
#105
0'
#110
b1 +
0!
0%
b0 *
b101 #
b101 -
1'
#115
0'
#120
1"
b0 #
b0 -
b1 *
1'
#125
0'
#130
b1 $
b1 ,
1'
#135
0'
#140
b10 $
b10 ,
1'
#145
0'
#150
b11 $
b11 ,
1'
#155
0'
#160
b10 +
1&
b100 $
b100 ,
1'
#165
0'
#170
0"
1!
0&
b10 *
b101 $
b101 ,
1'
#175
0'
#180
b0 $
b0 ,
b1 #
b1 -
1'
#185
0'
#190
b10 #
b10 -
1'
#195
0'
#200
b11 #
b11 -
1'
#205
0'
#210
b0 +
1%
b100 #
b100 -
1'
