design/image.v
module image(
input               clk,
input               camera_en,
output reg          data_valid,
output reg [7:0]    data_out);


parameter N = 450, M = 600;

reg [7:0] mem[3*N*M:0];
integer ptr;

initial
begin
 $readmemh("../res/data1.txt", mem);
 ptr <= 0;
end

always @(posedge clk)
begin
 if (camera_en)
 begin
  data_valid <= 1'b1;
  data_out <= mem[ptr];
  ptr <= ptr + 1;
 end
 else
 begin
  data_valid <= 0;
  ptr <= 0;
  data_out <= 8'hzz;
 end
 if (ptr == ((N*M*3) - 1))
 begin
  ptr <= 0;
 end
end
endmodule

testbenches/image_tb.v
module image_tb();

reg clk;
reg camera_en;
wire data_valid;
wire [7:0] data_out;

image UUT(clk, camera_en, data_valid, data_out);

initial
begin
 clk = 0;
 $dumpfile("vcd/image.vcd");
 $dumpvars(0, image_tb);
 camera_en = 0;
 #2;
 camera_en = 1;
 #1000;
 $finish;
end

always
begin
 clk = ~clk;
 #1;
end
endmodule

vcd/image.vcd
$date
	Sat May  1 13:55:49 2021
$end
$version
	Icarus Verilog
$end
$timescale
	1s
$end
$scope module image_tb $end
$var wire 1 ! data_valid $end
$var wire 8 " data_out [7:0] $end
$var reg 1 # camera_en $end
$var reg 1 $ clk $end
$scope module UUT $end
$var wire 1 # camera_en $end
$var wire 1 $ clk $end
$var reg 8 % data_out [7:0] $end
$var reg 1 ! data_valid $end
$var integer 32 & ptr [31:0] $end
$upscope $end
$upscope $end
$enddefinitions $end
#0
$dumpvars
b0 &
bz %
1$
0#
bz "
0!
$end
#1
0$
#2
b1 &
b10111100 "
b10111100 %
1!
1$
1#
#3
0$
#4
b10 &
b100111 "
b100111 %
1$
#5
0$
#6
b11 &
b10000001 "
b10000001 %
1$
#7
0$
#8
b100 &
b11111111 "
b11111111 %
1$
#9
0$
#10
b101 &
b11001110 "
b11001110 %
1$
#11
0$
#12
b110 &
b11111 "
b11111 %
1$
#13
0$
#14
b111 &
b11100000 "
b11100000 %
1$
#15
0$
#16
b1000 &
b10101001 "
b10101001 %
1$
#17
0$
#18
b1001 &
b111000 "
b111000 %
1$
#19
0$
#20
b1010 &
b101011 "
b101011 %
1$
#21
0$
#22
b1011 &
b11010100 "
b11010100 %
1$
#23
0$
#24
b1100 &
b10001 "
b10001 %
1$
#25
0$
#26
b1101 &
b10000 "
b10000 %
1$
#27
0$
#28
b1110 &
b1111 "
b1111 %
1$
#29
0$
#30
b1111 &
b1101110 "
b1101110 %
1$
#31
0$
#32
b10000 &
b10111111 "
b10111111 %
1$
#33
0$
#34
b10001 &
b1010000 "
b1010000 %
1$
#35
0$
#36
b10010 &
b10100011 "
b10100011 %
1$
#37
0$
#38
b10011 &
b1000101 "
b1000101 %
1$
#39
0$
#40
b10100 &
b101100 "
b101100 %
1$
#41
0$
#42
b10101 &
b1000100 "
b1000100 %
1$
#43
0$
#44
b10110 &
b1 "
b1 %
1$
#45
0$
#46
b10111 &
b100001 "
b100001 %
1$
#47
0$
#48
b11000 &
b11011111 "
b11011111 %
1$
#49
0$
#50
b11001 &
b11110 "
b11110 %
1$
#51
0$
#52
b11010 &
b1111111 "
b1111111 %
1$
#53
0$
#54
b11011 &
b10000000 "
b10000000 %
1$
#55
0$
#56
b11100 &
b111001 "
b111001 %
1$
#57
0$
#58
b11101 &
b1001000 "
b1001000 %
1$
#59
0$
#60
b11110 &
b11001011 "
b11001011 %
1$
#61
0$
#62
b11111 &
b11000100 "
b11000100 %
1$
#63
0$
#64
b100000 &
b11001100 "
b11001100 %
1$
#65
0$
#66
b100001 &
b10001111 "
b10001111 %
1$
#67
0$
#68
b100010 &
b11110010 "
b11110010 %
1$
#69
0$
#70
b100011 &
b11000100 "
b11000100 %
1$
#71
0$
#72
b100100 &
b10000 "
b10000 %
1$
#73
0$
#74
b100101 &
b11100001 "
b11100001 %
1$
#75
0$
#76
b100110 &
b10100000 "
b10100000 %
1$
#77
0$
#78
b100111 &
b110000 "
b110000 %
1$
#79
0$
#80
b101000 &
b100100 "
b100100 %
1$
#81
0$
#82
b101001 &
b11010110 "
b11010110 %
1$
#83
0$
#84
b101010 &
b10110 "
b10110 %
1$
#85
0$
#86
b101011 &
b10010001 "
b10010001 %
1$
#87
0$
#88
b101100 &
b11111001 "
b11111001 %
1$
#89
0$
#90
b101101 &
b1000011 "
b1000011 %
1$
#91
0$
#92
b101110 &
b10011 "
b10011 %
1$
#93
0$
#94
b101111 &
b11100000 "
b11100000 %
1$
#95
0$
#96
b110000 &
b10100010 "
b10100010 %
1$
#97
0$
#98
b110001 &
b111000 "
b111000 %
1$
#99
0$
#100
b110010 &
b101111 "
b101111 %
1$
#101
0$
#102
b110011 &
b11010100 "
b11010100 %
1$
#103
0$
#104
b110100 &
b10101 "
b10101 %
1$
#105
0$
#106
b110101 &
b10001100 "
b10001100 %
1$
#107
0$
#108
b110110 &
b11111111 "
b11111111 %
1$
#109
0$
#110
b110111 &
b11000001 "
b11000001 %
1$
#111
0$
#112
b111000 &
b11111 "
b11111 %
1$
#113
0$
#114
b111001 &
b11100101 "
b11100101 %
1$
#115
0$
#116
b111010 &
b10101001 "
b10101001 %
1$
#117
0$
#118
b111011 &
b111011 "
b111011 %
1$
#119
0$
#120
b111100 &
b101011 "
b101011 %
1$
#121
0$
#122
b111101 &
b11011101 "
b11011101 %
1$
#123
0$
#124
b111110 &
b10001 "
b10001 %
1$
#125
0$
#126
b111111 &
b10001110 "
b10001110 %
1$
#127
0$
#128
b1000000 &
b11111111 "
b11111111 %
1$
#129
0$
#130
b1000001 &
b11001010 "
b11001010 %
1$
#131
0$
#132
b1000010 &
b11111 "
b11111 %
1$
#133
0$
#134
b1000011 &
b11101110 "
b11101110 %
1$
#135
0$
#136
b1000100 &
b10101001 "
b10101001 %
1$
#137
0$
#138
b1000101 &
b110111 "
b110111 %
1$
#139
0$
#140
b1000110 &
b101011 "
b101011 %
1$
#141
0$
#142
b1000111 &
b11100100 "
b11100100 %
1$
#143
0$
#144
b1001000 &
b10001 "
b10001 %
1$
#145
0$
#146
b1001001 &
b11100001 "
b11100001 %
1$
#147
0$
#148
b1001010 &
b11111111 "
b11111111 %
1$
#149
0$
#150
0!
b0 &
b11011110 "
b11011110 %
1$
#151
0$
#152
b1 &
b10111100 "
b10111100 %
1!
1$
#153
0$
#154
b10 &
b100111 "
b100111 %
1$
#155
0$
#156
b11 &
b10000001 "
b10000001 %
1$
#157
0$
#158
b100 &
b11111111 "
b11111111 %
1$
#159
0$
#160
b101 &
b11001110 "
b11001110 %
1$
#161
0$
#162
b110 &
b11111 "
b11111 %
1$
#163
0$
#164
b111 &
b11100000 "
b11100000 %
1$
#165
0$
#166
b1000 &
b10101001 "
b10101001 %
1$
#167
0$
#168
b1001 &
b111000 "
b111000 %
1$
#169
0$
#170
b1010 &
b101011 "
b101011 %
1$
#171
0$
#172
b1011 &
b11010100 "
b11010100 %
1$
#173
0$
#174
b1100 &
b10001 "
b10001 %
1$
#175
0$
#176
b1101 &
b10000 "
b10000 %
1$
#177
0$
#178
b1110 &
b1111 "
b1111 %
1$
#179
0$
#180
b1111 &
b1101110 "
b1101110 %
1$
#181
0$
#182
b10000 &
b10111111 "
b10111111 %
1$
#183
0$
#184
b10001 &
b1010000 "
b1010000 %
1$
#185
0$
#186
b10010 &
b10100011 "
b10100011 %
1$
#187
0$
#188
b10011 &
b1000101 "
b1000101 %
1$
#189
0$
#190
b10100 &
b101100 "
b101100 %
1$
#191
0$
#192
b10101 &
b1000100 "
b1000100 %
1$
#193
0$
#194
b10110 &
b1 "
b1 %
1$
#195
0$
#196
b10111 &
b100001 "
b100001 %
1$
#197
0$
#198
b11000 &
b11011111 "
b11011111 %
1$
#199
0$
#200
b11001 &
b11110 "
b11110 %
1$
#201
0$
#202
b11010 &
b1111111 "
b1111111 %
1$
#203
0$
#204
b11011 &
b10000000 "
b10000000 %
1$
#205
0$
#206
b11100 &
b111001 "
b111001 %
1$
#207
0$
#208
b11101 &
b1001000 "
b1001000 %
1$
#209
0$
#210
b11110 &
b11001011 "
b11001011 %
1$
#211
0$
#212
b11111 &
b11000100 "
b11000100 %
1$
#213
0$
#214
b100000 &
b11001100 "
b11001100 %
1$
#215
0$
#216
b100001 &
b10001111 "
b10001111 %
1$
#217
0$
#218
b100010 &
b11110010 "
b11110010 %
1$
#219
0$
#220
b100011 &
b11000100 "
b11000100 %
1$
#221
0$
#222
b100100 &
b10000 "
b10000 %
1$
#223
0$
#224
b100101 &
b11100001 "
b11100001 %
1$
#225
0$
#226
b100110 &
b10100000 "
b10100000 %
1$
#227
0$
#228
b100111 &
b110000 "
b110000 %
1$
#229
0$
#230
b101000 &
b100100 "
b100100 %
1$
#231
0$
#232
b101001 &
b11010110 "
b11010110 %
1$
#233
0$
#234
b101010 &
b10110 "
b10110 %
1$
#235
0$
#236
b101011 &
b10010001 "
b10010001 %
1$
#237
0$
#238
b101100 &
b11111001 "
b11111001 %
1$
#239
0$
#240
b101101 &
b1000011 "
b1000011 %
1$
#241
0$
#242
b101110 &
b10011 "
b10011 %
1$
#243
0$
#244
b101111 &
b11100000 "
b11100000 %
1$
#245
0$
#246
b110000 &
b10100010 "
b10100010 %
1$
#247
0$
#248
b110001 &
b111000 "
b111000 %
1$
#249
0$
#250
b110010 &
b101111 "
b101111 %
1$
#251
0$
#252
b110011 &
b11010100 "
b11010100 %
1$
#253
0$
#254
b110100 &
b10101 "
b10101 %
1$
#255
0$
#256
b110101 &
b10001100 "
b10001100 %
1$
#257
0$
#258
b110110 &
b11111111 "
b11111111 %
1$
#259
0$
#260
b110111 &
b11000001 "
b11000001 %
1$
#261
0$
#262
b111000 &
b11111 "
b11111 %
1$
#263
0$
#264
b111001 &
b11100101 "
b11100101 %
1$
#265
0$
#266
b111010 &
b10101001 "
b10101001 %
1$
#267
0$
#268
b111011 &
b111011 "
b111011 %
1$
#269
0$
#270
b111100 &
b101011 "
b101011 %
1$
#271
0$
#272
b111101 &
b11011101 "
b11011101 %
1$
#273
0$
#274
b111110 &
b10001 "
b10001 %
1$
#275
0$
#276
b111111 &
b10001110 "
b10001110 %
1$
#277
0$
#278
b1000000 &
b11111111 "
b11111111 %
1$
#279
0$
#280
b1000001 &
b11001010 "
b11001010 %
1$
#281
0$
#282
b1000010 &
b11111 "
b11111 %
1$
#283
0$
#284
b1000011 &
b11101110 "
b11101110 %
1$
#285
0$
#286
b1000100 &
b10101001 "
b10101001 %
1$
#287
0$
#288
b1000101 &
b110111 "
b110111 %
1$
#289
0$
#290
b1000110 &
b101011 "
b101011 %
1$
#291
0$
#292
b1000111 &
b11100100 "
b11100100 %
1$
#293
0$
#294
b1001000 &
b10001 "
b10001 %
1$
#295
0$
#296
b1001001 &
b11100001 "
b11100001 %
1$
#297
0$
#298
b1001010 &
b11111111 "
b11111111 %
1$
#299
0$
#300
0!
b0 &
b11011110 "
b11011110 %
1$
#301
0$
#302
b1 &
b10111100 "
b10111100 %
1!
1$
#303
0$
#304
b10 &
b100111 "
b100111 %
1$
#305
0$
#306
b11 &
b10000001 "
b10000001 %
1$
#307
0$
#308
b100 &
b11111111 "
b11111111 %
1$
#309
0$
#310
b101 &
b11001110 "
b11001110 %
1$
#311
0$
#312
b110 &
b11111 "
b11111 %
1$
#313
0$
#314
b111 &
b11100000 "
b11100000 %
1$
#315
0$
#316
b1000 &
b10101001 "
b10101001 %
1$
#317
0$
#318
b1001 &
b111000 "
b111000 %
1$
#319
0$
#320
b1010 &
b101011 "
b101011 %
1$
#321
0$
#322
b1011 &
b11010100 "
b11010100 %
1$
#323
0$
#324
b1100 &
b10001 "
b10001 %
1$
#325
0$
#326
b1101 &
b10000 "
b10000 %
1$
#327
0$
#328
b1110 &
b1111 "
b1111 %
1$
#329
0$
#330
b1111 &
b1101110 "
b1101110 %
1$
#331
0$
#332
b10000 &
b10111111 "
b10111111 %
1$
#333
0$
#334
b10001 &
b1010000 "
b1010000 %
1$
#335
0$
#336
b10010 &
b10100011 "
b10100011 %
1$
#337
0$
#338
b10011 &
b1000101 "
b1000101 %
1$
#339
0$
#340
b10100 &
b101100 "
b101100 %
1$
#341
0$
#342
b10101 &
b1000100 "
b1000100 %
1$
#343
0$
#344
b10110 &
b1 "
b1 %
1$
#345
0$
#346
b10111 &
b100001 "
b100001 %
1$
#347
0$
#348
b11000 &
b11011111 "
b11011111 %
1$
#349
0$
#350
b11001 &
b11110 "
b11110 %
1$
#351
0$
#352
b11010 &
b1111111 "
b1111111 %
1$
#353
0$
#354
b11011 &
b10000000 "
b10000000 %
1$
#355
0$
#356
b11100 &
b111001 "
b111001 %
1$
#357
0$
#358
b11101 &
b1001000 "
b1001000 %
1$
#359
0$
#360
b11110 &
b11001011 "
b11001011 %
1$
#361
0$
#362
b11111 &
b11000100 "
b11000100 %
1$
#363
0$
#364
b100000 &
b11001100 "
b11001100 %
1$
#365
0$
#366
b100001 &
b10001111 "
b10001111 %
1$
#367
0$
#368
b100010 &
b11110010 "
b11110010 %
1$
#369
0$
#370
b100011 &
b11000100 "
b11000100 %
1$
#371
0$
#372
b100100 &
b10000 "
b10000 %
1$
#373
0$
#374
b100101 &
b11100001 "
b11100001 %
1$
#375
0$
#376
b100110 &
b10100000 "
b10100000 %
1$
#377
0$
#378
b100111 &
b110000 "
b110000 %
1$
#379
0$
#380
b101000 &
b100100 "
b100100 %
1$
#381
0$
#382
b101001 &
b11010110 "
b11010110 %
1$
#383
0$
#384
b101010 &
b10110 "
b10110 %
1$
#385
0$
#386
b101011 &
b10010001 "
b10010001 %
1$
#387
0$
#388
b101100 &
b11111001 "
b11111001 %
1$
#389
0$
#390
b101101 &
b1000011 "
b1000011 %
1$
#391
0$
#392
b101110 &
b10011 "
b10011 %
1$
#393
0$
#394
b101111 &
b11100000 "
b11100000 %
1$
#395
0$
#396
b110000 &
b10100010 "
b10100010 %
1$
#397
0$
#398
b110001 &
b111000 "
b111000 %
1$
#399
0$
#400
b110010 &
b101111 "
b101111 %
1$
#401
0$
#402
b110011 &
b11010100 "
b11010100 %
1$
#403
0$
#404
b110100 &
b10101 "
b10101 %
1$
#405
0$
#406
b110101 &
b10001100 "
b10001100 %
1$
#407
0$
#408
b110110 &
b11111111 "
b11111111 %
1$
#409
0$
#410
b110111 &
b11000001 "
b11000001 %
1$
#411
0$
#412
b111000 &
b11111 "
b11111 %
1$
#413
0$
#414
b111001 &
b11100101 "
b11100101 %
1$
#415
0$
#416
b111010 &
b10101001 "
b10101001 %
1$
#417
0$
#418
b111011 &
b111011 "
b111011 %
1$
#419
0$
#420
b111100 &
b101011 "
b101011 %
1$
#421
0$
#422
b111101 &
b11011101 "
b11011101 %
1$
#423
0$
#424
b111110 &
b10001 "
b10001 %
1$
#425
0$
#426
b111111 &
b10001110 "
b10001110 %
1$
#427
0$
#428
b1000000 &
b11111111 "
b11111111 %
1$
#429
0$
#430
b1000001 &
b11001010 "
b11001010 %
1$
#431
0$
#432
b1000010 &
b11111 "
b11111 %
1$
#433
0$
#434
b1000011 &
b11101110 "
b11101110 %
1$
#435
0$
#436
b1000100 &
b10101001 "
b10101001 %
1$
#437
0$
#438
b1000101 &
b110111 "
b110111 %
1$
#439
0$
#440
b1000110 &
b101011 "
b101011 %
1$
#441
0$
#442
b1000111 &
b11100100 "
b11100100 %
1$
#443
0$
#444
b1001000 &
b10001 "
b10001 %
1$
#445
0$
#446
b1001001 &
b11100001 "
b11100001 %
1$
#447
0$
#448
b1001010 &
b11111111 "
b11111111 %
1$
#449
0$
#450
0!
b0 &
b11011110 "
b11011110 %
1$
#451
0$
#452
b1 &
b10111100 "
b10111100 %
1!
1$
#453
0$
#454
b10 &
b100111 "
b100111 %
1$
#455
0$
#456
b11 &
b10000001 "
b10000001 %
1$
#457
0$
#458
b100 &
b11111111 "
b11111111 %
1$
#459
0$
#460
b101 &
b11001110 "
b11001110 %
1$
#461
0$
#462
b110 &
b11111 "
b11111 %
1$
#463
0$
#464
b111 &
b11100000 "
b11100000 %
1$
#465
0$
#466
b1000 &
b10101001 "
b10101001 %
1$
#467
0$
#468
b1001 &
b111000 "
b111000 %
1$
#469
0$
#470
b1010 &
b101011 "
b101011 %
1$
#471
0$
#472
b1011 &
b11010100 "
b11010100 %
1$
#473
0$
#474
b1100 &
b10001 "
b10001 %
1$
#475
0$
#476
b1101 &
b10000 "
b10000 %
1$
#477
0$
#478
b1110 &
b1111 "
b1111 %
1$
#479
0$
#480
b1111 &
b1101110 "
b1101110 %
1$
#481
0$
#482
b10000 &
b10111111 "
b10111111 %
1$
#483
0$
#484
b10001 &
b1010000 "
b1010000 %
1$
#485
0$
#486
b10010 &
b10100011 "
b10100011 %
1$
#487
0$
#488
b10011 &
b1000101 "
b1000101 %
1$
#489
0$
#490
b10100 &
b101100 "
b101100 %
1$
#491
0$
#492
b10101 &
b1000100 "
b1000100 %
1$
#493
0$
#494
b10110 &
b1 "
b1 %
1$
#495
0$
#496
b10111 &
b100001 "
b100001 %
1$
#497
0$
#498
b11000 &
b11011111 "
b11011111 %
1$
#499
0$
#500
b11001 &
b11110 "
b11110 %
1$
#501
0$
#502
b11010 &
b1111111 "
b1111111 %
1$
#503
0$
#504
b11011 &
b10000000 "
b10000000 %
1$
#505
0$
#506
b11100 &
b111001 "
b111001 %
1$
#507
0$
#508
b11101 &
b1001000 "
b1001000 %
1$
#509
0$
#510
b11110 &
b11001011 "
b11001011 %
1$
#511
0$
#512
b11111 &
b11000100 "
b11000100 %
1$
#513
0$
#514
b100000 &
b11001100 "
b11001100 %
1$
#515
0$
#516
b100001 &
b10001111 "
b10001111 %
1$
#517
0$
#518
b100010 &
b11110010 "
b11110010 %
1$
#519
0$
#520
b100011 &
b11000100 "
b11000100 %
1$
#521
0$
#522
b100100 &
b10000 "
b10000 %
1$
#523
0$
#524
b100101 &
b11100001 "
b11100001 %
1$
#525
0$
#526
b100110 &
b10100000 "
b10100000 %
1$
#527
0$
#528
b100111 &
b110000 "
b110000 %
1$
#529
0$
#530
b101000 &
b100100 "
b100100 %
1$
#531
0$
#532
b101001 &
b11010110 "
b11010110 %
1$
#533
0$
#534
b101010 &
b10110 "
b10110 %
1$
#535
0$
#536
b101011 &
b10010001 "
b10010001 %
1$
#537
0$
#538
b101100 &
b11111001 "
b11111001 %
1$
#539
0$
#540
b101101 &
b1000011 "
b1000011 %
1$
#541
0$
#542
b101110 &
b10011 "
b10011 %
1$
#543
0$
#544
b101111 &
b11100000 "
b11100000 %
1$
#545
0$
#546
b110000 &
b10100010 "
b10100010 %
1$
#547
0$
#548
b110001 &
b111000 "
b111000 %
1$
#549
0$
#550
b110010 &
b101111 "
b101111 %
1$
#551
0$
#552
b110011 &
b11010100 "
b11010100 %
1$
#553
0$
#554
b110100 &
b10101 "
b10101 %
1$
#555
0$
#556
b110101 &
b10001100 "
b10001100 %
1$
#557
0$
#558
b110110 &
b11111111 "
b11111111 %
1$
#559
0$
#560
b110111 &
b11000001 "
b11000001 %
1$
#561
0$
#562
b111000 &
b11111 "
b11111 %
1$
#563
0$
#564
b111001 &
b11100101 "
b11100101 %
1$
#565
0$
#566
b111010 &
b10101001 "
b10101001 %
1$
#567
0$
#568
b111011 &
b111011 "
b111011 %
1$
#569
0$
#570
b111100 &
b101011 "
b101011 %
1$
#571
0$
#572
b111101 &
b11011101 "
b11011101 %
1$
#573
0$
#574
b111110 &
b10001 "
b10001 %
1$
#575
0$
#576
b111111 &
b10001110 "
b10001110 %
1$
#577
0$
#578
b1000000 &
b11111111 "
b11111111 %
1$
#579
0$
#580
b1000001 &
b11001010 "
b11001010 %
1$
#581
0$
#582
b1000010 &
b11111 "
b11111 %
1$
#583
0$
#584
b1000011 &
b11101110 "
b11101110 %
1$
#585
0$
#586
b1000100 &
b10101001 "
b10101001 %
1$
#587
0$
#588
b1000101 &
b110111 "
b110111 %
1$
#589
0$
#590
b1000110 &
b101011 "
b101011 %
1$
#591
0$
#592
b1000111 &
b11100100 "
b11100100 %
1$
#593
0$
#594
b1001000 &
b10001 "
b10001 %
1$
#595
0$
#596
b1001001 &
b11100001 "
b11100001 %
1$
#597
0$
#598
b1001010 &
b11111111 "
b11111111 %
1$
#599
0$
#600
0!
b0 &
b11011110 "
b11011110 %
1$
#601
0$
#602
b1 &
b10111100 "
b10111100 %
1!
1$
#603
0$
#604
b10 &
b100111 "
b100111 %
1$
#605
0$
#606
b11 &
b10000001 "
b10000001 %
1$
#607
0$
#608
b100 &
b11111111 "
b11111111 %
1$
#609
0$
#610
b101 &
b11001110 "
b11001110 %
1$
#611
0$
#612
b110 &
b11111 "
b11111 %
1$
#613
0$
#614
b111 &
b11100000 "
b11100000 %
1$
#615
0$
#616
b1000 &
b10101001 "
b10101001 %
1$
#617
0$
#618
b1001 &
b111000 "
b111000 %
1$
#619
0$
#620
b1010 &
b101011 "
b101011 %
1$
#621
0$
#622
b1011 &
b11010100 "
b11010100 %
1$
#623
0$
#624
b1100 &
b10001 "
b10001 %
1$
#625
0$
#626
b1101 &
b10000 "
b10000 %
1$
#627
0$
#628
b1110 &
b1111 "
b1111 %
1$
#629
0$
#630
b1111 &
b1101110 "
b1101110 %
1$
#631
0$
#632
b10000 &
b10111111 "
b10111111 %
1$
#633
0$
#634
b10001 &
b1010000 "
b1010000 %
1$
#635
0$
#636
b10010 &
b10100011 "
b10100011 %
1$
#637
0$
#638
b10011 &
b1000101 "
b1000101 %
1$
#639
0$
#640
b10100 &
b101100 "
b101100 %
1$
#641
0$
#642
b10101 &
b1000100 "
b1000100 %
1$
#643
0$
#644
b10110 &
b1 "
b1 %
1$
#645
0$
#646
b10111 &
b100001 "
b100001 %
1$
#647
0$
#648
b11000 &
b11011111 "
b11011111 %
1$
#649
0$
#650
b11001 &
b11110 "
b11110 %
1$
#651
0$
#652
b11010 &
b1111111 "
b1111111 %
1$
#653
0$
#654
b11011 &
b10000000 "
b10000000 %
1$
#655
0$
#656
b11100 &
b111001 "
b111001 %
1$
#657
0$
#658
b11101 &
b1001000 "
b1001000 %
1$
#659
0$
#660
b11110 &
b11001011 "
b11001011 %
1$
#661
0$
#662
b11111 &
b11000100 "
b11000100 %
1$
#663
0$
#664
b100000 &
b11001100 "
b11001100 %
1$
#665
0$
#666
b100001 &
b10001111 "
b10001111 %
1$
#667
0$
#668
b100010 &
b11110010 "
b11110010 %
1$
#669
0$
#670
b100011 &
b11000100 "
b11000100 %
1$
#671
0$
#672
b100100 &
b10000 "
b10000 %
1$
#673
0$
#674
b100101 &
b11100001 "
b11100001 %
1$
#675
0$
#676
b100110 &
b10100000 "
b10100000 %
1$
#677
0$
#678
b100111 &
b110000 "
b110000 %
1$
#679
0$
#680
b101000 &
b100100 "
b100100 %
1$
#681
0$
#682
b101001 &
b11010110 "
b11010110 %
1$
#683
0$
#684
b101010 &
b10110 "
b10110 %
1$
#685
0$
#686
b101011 &
b10010001 "
b10010001 %
1$
#687
0$
#688
b101100 &
b11111001 "
b11111001 %
1$
#689
0$
#690
b101101 &
b1000011 "
b1000011 %
1$
#691
0$
#692
b101110 &
b10011 "
b10011 %
1$
#693
0$
#694
b101111 &
b11100000 "
b11100000 %
1$
#695
0$
#696
b110000 &
b10100010 "
b10100010 %
1$
#697
0$
#698
b110001 &
b111000 "
b111000 %
1$
#699
0$
#700
b110010 &
b101111 "
b101111 %
1$
#701
0$
#702
b110011 &
b11010100 "
b11010100 %
1$
#703
0$
#704
b110100 &
b10101 "
b10101 %
1$
#705
0$
#706
b110101 &
b10001100 "
b10001100 %
1$
#707
0$
#708
b110110 &
b11111111 "
b11111111 %
1$
#709
0$
#710
b110111 &
b11000001 "
b11000001 %
1$
#711
0$
#712
b111000 &
b11111 "
b11111 %
1$
#713
0$
#714
b111001 &
b11100101 "
b11100101 %
1$
#715
0$
#716
b111010 &
b10101001 "
b10101001 %
1$
#717
0$
#718
b111011 &
b111011 "
b111011 %
1$
#719
0$
#720
b111100 &
b101011 "
b101011 %
1$
#721
0$
#722
b111101 &
b11011101 "
b11011101 %
1$
#723
0$
#724
b111110 &
b10001 "
b10001 %
1$
#725
0$
#726
b111111 &
b10001110 "
b10001110 %
1$
#727
0$
#728
b1000000 &
b11111111 "
b11111111 %
1$
#729
0$
#730
b1000001 &
b11001010 "
b11001010 %
1$
#731
0$
#732
b1000010 &
b11111 "
b11111 %
1$
#733
0$
#734
b1000011 &
b11101110 "
b11101110 %
1$
#735
0$
#736
b1000100 &
b10101001 "
b10101001 %
1$
#737
0$
#738
b1000101 &
b110111 "
b110111 %
1$
#739
0$
#740
b1000110 &
b101011 "
b101011 %
1$
#741
0$
#742
b1000111 &
b11100100 "
b11100100 %
1$
#743
0$
#744
b1001000 &
b10001 "
b10001 %
1$
#745
0$
#746
b1001001 &
b11100001 "
b11100001 %
1$
#747
0$
#748
b1001010 &
b11111111 "
b11111111 %
1$
#749
0$
#750
0!
b0 &
b11011110 "
b11011110 %
1$
#751
0$
#752
b1 &
b10111100 "
b10111100 %
1!
1$
#753
0$
#754
b10 &
b100111 "
b100111 %
1$
#755
0$
#756
b11 &
b10000001 "
b10000001 %
1$
#757
0$
#758
b100 &
b11111111 "
b11111111 %
1$
#759
0$
#760
b101 &
b11001110 "
b11001110 %
1$
#761
0$
#762
b110 &
b11111 "
b11111 %
1$
#763
0$
#764
b111 &
b11100000 "
b11100000 %
1$
#765
0$
#766
b1000 &
b10101001 "
b10101001 %
1$
#767
0$
#768
b1001 &
b111000 "
b111000 %
1$
#769
0$
#770
b1010 &
b101011 "
b101011 %
1$
#771
0$
#772
b1011 &
b11010100 "
b11010100 %
1$
#773
0$
#774
b1100 &
b10001 "
b10001 %
1$
#775
0$
#776
b1101 &
b10000 "
b10000 %
1$
#777
0$
#778
b1110 &
b1111 "
b1111 %
1$
#779
0$
#780
b1111 &
b1101110 "
b1101110 %
1$
#781
0$
#782
b10000 &
b10111111 "
b10111111 %
1$
#783
0$
#784
b10001 &
b1010000 "
b1010000 %
1$
#785
0$
#786
b10010 &
b10100011 "
b10100011 %
1$
#787
0$
#788
b10011 &
b1000101 "
b1000101 %
1$
#789
0$
#790
b10100 &
b101100 "
b101100 %
1$
#791
0$
#792
b10101 &
b1000100 "
b1000100 %
1$
#793
0$
#794
b10110 &
b1 "
b1 %
1$
#795
0$
#796
b10111 &
b100001 "
b100001 %
1$
#797
0$
#798
b11000 &
b11011111 "
b11011111 %
1$
#799
0$
#800
b11001 &
b11110 "
b11110 %
1$
#801
0$
#802
b11010 &
b1111111 "
b1111111 %
1$
#803
0$
#804
b11011 &
b10000000 "
b10000000 %
1$
#805
0$
#806
b11100 &
b111001 "
b111001 %
1$
#807
0$
#808
b11101 &
b1001000 "
b1001000 %
1$
#809
0$
#810
b11110 &
b11001011 "
b11001011 %
1$
#811
0$
#812
b11111 &
b11000100 "
b11000100 %
1$
#813
0$
#814
b100000 &
b11001100 "
b11001100 %
1$
#815
0$
#816
b100001 &
b10001111 "
b10001111 %
1$
#817
0$
#818
b100010 &
b11110010 "
b11110010 %
1$
#819
0$
#820
b100011 &
b11000100 "
b11000100 %
1$
#821
0$
#822
b100100 &
b10000 "
b10000 %
1$
#823
0$
#824
b100101 &
b11100001 "
b11100001 %
1$
#825
0$
#826
b100110 &
b10100000 "
b10100000 %
1$
#827
0$
#828
b100111 &
b110000 "
b110000 %
1$
#829
0$
#830
b101000 &
b100100 "
b100100 %
1$
#831
0$
#832
b101001 &
b11010110 "
b11010110 %
1$
#833
0$
#834
b101010 &
b10110 "
b10110 %
1$
#835
0$
#836
b101011 &
b10010001 "
b10010001 %
1$
#837
0$
#838
b101100 &
b11111001 "
b11111001 %
1$
#839
0$
#840
b101101 &
b1000011 "
b1000011 %
1$
#841
0$
#842
b101110 &
b10011 "
b10011 %
1$
#843
0$
#844
b101111 &
b11100000 "
b11100000 %
1$
#845
0$
#846
b110000 &
b10100010 "
b10100010 %
1$
#847
0$
#848
b110001 &
b111000 "
b111000 %
1$
#849
0$
#850
b110010 &
b101111 "
b101111 %
1$
#851
0$
#852
b110011 &
b11010100 "
b11010100 %
1$
#853
0$
#854
b110100 &
b10101 "
b10101 %
1$
#855
0$
#856
b110101 &
b10001100 "
b10001100 %
1$
#857
0$
#858
b110110 &
b11111111 "
b11111111 %
1$
#859
0$
#860
b110111 &
b11000001 "
b11000001 %
1$
#861
0$
#862
b111000 &
b11111 "
b11111 %
1$
#863
0$
#864
b111001 &
b11100101 "
b11100101 %
1$
#865
0$
#866
b111010 &
b10101001 "
b10101001 %
1$
#867
0$
#868
b111011 &
b111011 "
b111011 %
1$
#869
0$
#870
b111100 &
b101011 "
b101011 %
1$
#871
0$
#872
b111101 &
b11011101 "
b11011101 %
1$
#873
0$
#874
b111110 &
b10001 "
b10001 %
1$
#875
0$
#876
b111111 &
b10001110 "
b10001110 %
1$
#877
0$
#878
b1000000 &
b11111111 "
b11111111 %
1$
#879
0$
#880
b1000001 &
b11001010 "
b11001010 %
1$
#881
0$
#882
b1000010 &
b11111 "
b11111 %
1$
#883
0$
#884
b1000011 &
b11101110 "
b11101110 %
1$
#885
0$
#886
b1000100 &
b10101001 "
b10101001 %
1$
#887
0$
#888
b1000101 &
b110111 "
b110111 %
1$
#889
0$
#890
b1000110 &
b101011 "
b101011 %
1$
#891
0$
#892
b1000111 &
b11100100 "
b11100100 %
1$
#893
0$
#894
b1001000 &
b10001 "
b10001 %
1$
#895
0$
#896
b1001001 &
b11100001 "
b11100001 %
1$
#897
0$
#898
b1001010 &
b11111111 "
b11111111 %
1$
#899
0$
#900
0!
b0 &
b11011110 "
b11011110 %
1$
#901
0$
#902
b1 &
b10111100 "
b10111100 %
1!
1$
#903
0$
#904
b10 &
b100111 "
b100111 %
1$
#905
0$
#906
b11 &
b10000001 "
b10000001 %
1$
#907
0$
#908
b100 &
b11111111 "
b11111111 %
1$
